dhm_module_base/__init__.py
dhm_module_base/cli.py
dhm_module_base/helpers.py
dhm_module_base/options.py
dhm_module_base/settings.py
dhm_module_base/configs/dummy.ini
dhm_module_base-0.0.1.dist-info/LICENSE
dhm_module_base-0.0.1.dist-info/METADATA
dhm_module_base-0.0.1.dist-info/WHEEL
dhm_module_base-0.0.1.dist-info/entry_points.txt
dhm_module_base-0.0.1.dist-info/top_level.txt
dhm_module_base-0.0.1.dist-info/RECORD
